shyurer/__init__.py
shyurer-0.1.5.dist-info/METADATA
shyurer-0.1.5.dist-info/WHEEL
shyurer-0.1.5.dist-info/top_level.txt
shyurer-0.1.5.dist-info/RECORD
