Metadata-Version: 2.4
Name: shyurer
Version: 0.1.5
Summary: Shyurer Engine Banner
Requires-Python: >=3.7
Requires-Dist: colorama
Dynamic: requires-dist
Dynamic: requires-python
Dynamic: summary
